Metadata-Version: 1.1
Name: django-allauth-mandrill
Version: 0.1.4
Summary: Django Allauth account adapter for sending email using Mandrill templates
Home-page: https://github.com/xncbf/django-allauth-mandrill
Author: Francis Kim<xncbf12@gmail.com>
Author-email: xncbf12@gmail.com
License: Apache
Keywords: django,allauth,mailchimp,mandrill,email,djrill
Platform: UNKNOWN
Classifier: Development Status :: 3 - Alpha
Classifier: Framework :: Django
Classifier: License :: OSI Approved :: Apache Software License
Classifier: Programming Language :: Python
Classifier: Programming Language :: Python :: 2.7
Classifier: Programming Language :: Python :: 3.2
Classifier: Programming Language :: Python :: 3.3
Classifier: Programming Language :: Python :: 3.4
Classifier: Operating System :: OS Independent
Classifier: Intended Audience :: Developers
Classifier: Topic :: Software Development :: Libraries :: Python Modules
Classifier: Environment :: Web Environment
